realnet/__init__.py
realnet/__main__.py
realnet/realnet.py
realnet/cmd/__init__.py
realnet/cmd/create.py
realnet/cmd/get.py
realnet/cmd/info.py
realnet/cmd/runner.py
realnet/cmd/server.py
realnet/core/__init__.py
realnet/core/acl.py
realnet/core/config.py
realnet/core/hierarchy.py
realnet/core/provider.py
realnet/core/type.py
realnet/provider/__init__.py
realnet/provider/aws/__init__.py
realnet/provider/aws/data.py
realnet/provider/generic/__init__.py
realnet/provider/generic/endpoint.py
realnet/provider/generic/importer.py
realnet/provider/generic/resource.py
realnet/provider/json/__init__.py
realnet/provider/sql/__init__.py
realnet/provider/sql/client.py
realnet/provider/sql/init.py
realnet/provider/sql/models.py
realnet/provider/sql/org.py
realnet/provider/sql/orgs.py
realnet/provider/sql/roles.py
realnet/provider/sql/type.py
realnet/provider/sql/utility.py
realnet/provider/sql/postgres/__init__.py
realnet/provider/sql/postgres/item.py
realnet/provider/sql/sqlite/__init__.py
realnet/provider/xml/__init__.py
realnet/provider/yaml/__init__.py
realnet/resource/__init__.py
realnet/resource/accounts/__init__.py
realnet/resource/accounts/accounts.py
realnet/resource/apps/__init__.py
realnet/resource/apps/apps.py
realnet/resource/attributes/__init__.py
realnet/resource/attributes/attributes.py
realnet/resource/auths/__init__.py
realnet/resource/auths/auths.py
realnet/resource/chatgpt/__init__.py
realnet/resource/chatgpt/chatgpt.py
realnet/resource/clients/__init__.py
realnet/resource/clients/clients.py
realnet/resource/ctrls/__init__.py
realnet/resource/ctrls/ctrls.py
realnet/resource/endpoints/__init__.py
realnet/resource/endpoints/endpoints.py
realnet/resource/files/__init__.py
realnet/resource/files/files.py
realnet/resource/forms/__init__.py
realnet/resource/forms/forms.py
realnet/resource/gltf/__init__.py
realnet/resource/gltf/export.py
realnet/resource/gltf/gltf.py
realnet/resource/groups/__init__.py
realnet/resource/groups/groups.py
realnet-0.0.114.dist-info/LICENSE
realnet-0.0.114.dist-info/METADATA
realnet-0.0.114.dist-info/WHEEL
realnet-0.0.114.dist-info/entry_points.txt
realnet-0.0.114.dist-info/top_level.txt
realnet-0.0.114.dist-info/RECORD
