Metadata-Version: 2.1
Name: realnet
Version: 0.0.114
Summary: Realnet command line interface
Home-page: https://github.com/virtual-space/realnet
Author: Marko Laban
Author-email: marko.laban@l33tsystems.com
License: BSD
Classifier: License :: OSI Approved :: BSD License
Classifier: Programming Language :: Python :: 3
Classifier: Programming Language :: Python :: 3.10
License-File: LICENSE
Requires-Dist: python-dotenv
Requires-Dist: urllib3 (==1.25.4)
Requires-Dist: boto3
Requires-Dist: Flask (==2.2.2)
Requires-Dist: SQLAlchemy (==1.4.23)
Requires-Dist: psycopg2-binary
Requires-Dist: sqlalchemy-serializer
Requires-Dist: shapely (==1.8.5)
Requires-Dist: GeoAlchemy2
Requires-Dist: Werkzeug
Requires-Dist: authlib
Requires-Dist: flask-cors
Requires-Dist: bootstrap-flask
Requires-Dist: requests
Requires-Dist: pygltflib
Requires-Dist: trimesh
Requires-Dist: scipy
Requires-Dist: Pillow (==9.4.0)
Requires-Dist: pillow-heif (==0.7.0)
Requires-Dist: gunicorn (==20.1.0)
